liblaf/kiwi/__init__.py
liblaf/kiwi/__init__.pyi
liblaf/kiwi/__main__.py
liblaf/kiwi/_version.py
liblaf/kiwi/_version.pyi
liblaf/kiwi/py.typed
liblaf/kiwi/app/__init__.py
liblaf/kiwi/app/__init__.pyi
liblaf/kiwi/app/_app.py
liblaf/kiwi/app/_hello.py
liblaf/kiwi/app/ufw_geomap/__init__.py
liblaf/kiwi/app/ufw_geomap/__init__.pyi
liblaf/kiwi/app/ufw_geomap/_app.py
liblaf/kiwi/app/ufw_geomap/_impl.py
liblaf/kiwi/app/ufw_geomap/_load.py
liblaf/kiwi/utils/__init__.py
liblaf/kiwi/utils/__init__.pyi
liblaf/kiwi/utils/_dirs.py
liblaf_kiwi-0.1.1.dist-info/METADATA
liblaf_kiwi-0.1.1.dist-info/WHEEL
liblaf_kiwi-0.1.1.dist-info/entry_points.txt
liblaf_kiwi-0.1.1.dist-info/licenses/LICENSE
liblaf_kiwi-0.1.1.dist-info/RECORD
