Metadata-Version: 2.4
Name: liblaf-kiwi
Version: 0.1.1
Summary: Add your description here
Project-URL: Changelog, https://github.com/liblaf/kiwi-python/blob/main/CHANGELOG.md
Project-URL: Documentation, https://liblaf.github.io/kiwi-python/
Project-URL: Homepage, https://github.com/liblaf/kiwi-python
Project-URL: Issue Tracker, https://github.com/liblaf/kiwi-python/issues
Project-URL: Release Notes, https://github.com/liblaf/kiwi-python/releases
Project-URL: Source Code, https://github.com/liblaf/kiwi-python
Author-email: liblaf <30631553+liblaf@users.noreply.github.com>
License-Expression: MIT
License-File: LICENSE
Classifier: Development Status :: 4 - Beta
Classifier: Intended Audience :: Developers
Classifier: License :: OSI Approved
Classifier: License :: OSI Approved :: MIT License
Classifier: Operating System :: OS Independent
Classifier: Programming Language :: Python
Classifier: Programming Language :: Python :: 3
Classifier: Programming Language :: Python :: 3.12
Classifier: Programming Language :: Python :: 3.13
Classifier: Typing :: Typed
Requires-Python: >=3.12
Requires-Dist: cyclopts<4,>=3.17.0
Requires-Dist: lazy-loader<0.5,>=0.4
Requires-Dist: liblaf-grapes<0.3,>=0.2.1
Requires-Dist: loguru<0.8,>=0.7.3
Requires-Dist: platformdirs>=4.3.8
Requires-Dist: pydantic<3,>=2.11.5
Requires-Dist: rich<15,>=14.0.0
Provides-Extra: all
Requires-Dist: folium>=0.19.7; extra == 'all'
Requires-Dist: geoip2>=5.1.0; extra == 'all'
Requires-Dist: polars>=1.30.0; extra == 'all'
Provides-Extra: ufw-geomap
Requires-Dist: folium>=0.19.7; extra == 'ufw-geomap'
Requires-Dist: geoip2>=5.1.0; extra == 'ufw-geomap'
Requires-Dist: polars>=1.30.0; extra == 'ufw-geomap'
